ddbox_remote/__init__.py
ddbox_remote/configs.py
ddbox_remote/data/__init__.py
ddbox_remote/data/torch.py
ddbox_remote/data/utils/__init__.py
ddbox_remote/data/utils/loaders.py
ddbox_remote/submissions.py
ddbox_remote/utils.py
ddbox_remote-0.1.0.dist-info/METADATA
ddbox_remote-0.1.0.dist-info/WHEEL
ddbox_remote-0.1.0.dist-info/RECORD
